mongodb_connect/__init__.py
mongodb_connect/mongo_crud.py
mongoDB_python_connector-0.0.1.dist-info/LICENSE
mongoDB_python_connector-0.0.1.dist-info/METADATA
mongoDB_python_connector-0.0.1.dist-info/WHEEL
mongoDB_python_connector-0.0.1.dist-info/top_level.txt
mongoDB_python_connector-0.0.1.dist-info/RECORD
